[
  {
    "name": "Andrea",
    "nickname": "Cioccolatino",
    "subscriptionYear": "2023",
    "games": [
      {
        "name": "Risiko",
        "yearOfRelease": "2003",
        "authors": ["Mauro Frizzi", "Aragosta Irachena"],
        "singleplayer": false,
        "minPlayers": "2",
        "maxPlayers": "9",
        "type": "competitive"
      },
      {
        "name": "Solitario",
        "yearOfRelease": "1999",
        "authors": ["Jamal Jamal", "Davide Bismuti"],
        "singleplayer": true,
        "minPlayers": "1",
        "maxPlayers": "1",
        "type": "singleplayer"
      },
      {
        "name": "Il debito del regno",
        "yearOfRelease": "2023",
        "authors": ["Zephyrus Edavane"],
        "singleplayer": false,
        "minPlayers": "2",
        "maxPlayers": "8",
        "type": "cooperative"
      }
    ],
    "wishlist": [
      {
        "name": "Borderlands 4",
        "yearOfRelease": "2027",
        "authors": ["Zephyrus Edavane", "Davide Bismuti"],
        "singleplayer": false,
        "minPlayers": "1",
        "maxPlayers": "4",
        "type": "cooperative"
      }
    ]
  },
  {
    "name": "Tommaso",
    "nickname": "TomTitor",
    "subscriptionYear": "2017",
    "games": [
      {
        "name": "Risiko",
        "yearOfRelease": "2003",
        "authors": ["Mauro Frizzi", "Aragosta Irachena"],
        "singleplayer": false,
        "minPlayers": "2",
        "maxPlayers": "9",
        "type": "competitive"
      },
      {
        "name": "COD WW2",
        "yearOfRelease": "2012",
        "authors": ["Mauro Frizzi", "Zephyrus Edavane", "Jamal Jamal"],
        "singleplayer": false,
        "minPlayers": "1",
        "maxPlayers": "4",
        "type": "semi-cooperative"
      }
    ],
    "wishlist": [
      {
        "name": "Solitario",
        "yearOfRelease": "1999",
        "authors": ["Jamal Jamal", "Davide Bismuti"],
        "singleplayer": true,
        "minPlayers": "1",
        "maxPlayers": "1",
        "type": "singleplayer"
      }
    ]
  },
  {
    "name": "Emilio",
    "nickname": "Emix05z",
    "subscriptionYear": "2020",
    "games": [
      {
        "name": "Risiko",
        "yearOfRelease": "2003",
        "authors": ["Mauro Frizzi", "Aragosta Irachena"],
        "singleplayer": false,
        "minPlayers": "2",
        "maxPlayers": "9",
        "type": "competitive"
      },
      {
        "name": "Solitario",
        "yearOfRelease": "1999",
        "authors": ["Jamal Jamal", "Davide Bismuti"],
        "singleplayer": true,
        "minPlayers": "1",
        "maxPlayers": "1",
        "type": "singleplayer"
      }
    ],
    "wishlist": []
  },
  {
    "name": "Yehor",
    "nickname": "vpdalu",
    "subscriptionYear": "2023",
    "games": [],
    "wishlist": []
  },
  {
    "name": "Luca",
    "nickname": "Lucaw44",
    "subscriptionYear": "2023",
    "games": [
      {
        "name": "Risiko",
        "yearOfRelease": "2003",
        "authors": ["Mauro Frizzi", "Aragosta Irachena"],
        "singleplayer": false,
        "minPlayers": "2",
        "maxPlayers": "9",
        "type": "competitive"
      },
      {
        "name": "Borderlands 4",
        "yearOfRelease": "2027",
        "authors": ["Zephyrus Edavane", "Davide Bismuti"],
        "singleplayer": false,
        "minPlayers": "1",
        "maxPlayers": "4",
        "type": "cooperative"
      },
      {
        "name": "COD WW2",
        "yearOfRelease": "2012",
        "authors": ["Mauro Frizzi", "Zephyrus Edavane", "Jamal Jamal"],
        "singleplayer": false,
        "minPlayers": "1",
        "maxPlayers": "4",
        "type": "semi-cooperative"
      }
    ],
    "wishlist": [
      {
        "name": "Solitario",
        "yearOfRelease": "1999",
        "authors": ["Jamal Jamal", "Davide Bismuti"],
        "singleplayer": true,
        "minPlayers": "1",
        "maxPlayers": "1",
        "type": "singleplayer"
      }
    ]
  },
  {
    "name": "Aldo",
    "nickname": "Giung",
    "subscriptionYear": "2023",
    "games": [
      {
        "name": "Risiko",
        "yearOfRelease": "2003",
        "authors": ["Mauro Frizzi", "Aragosta Irachena"],
        "singleplayer": false,
        "minPlayers": "2",
        "maxPlayers": "9",
        "type": "competitive"
      },
      {
        "name": "Solitario",
        "yearOfRelease": "1999",
        "authors": ["Jamal Jamal", "Davide Bismuti"],
        "singleplayer": true,
        "minPlayers": "1",
        "maxPlayers": "1",
        "type": "singleplayer"
      }
    ],
    "wishlist": [
      {
        "name": "Il debito del regno",
        "yearOfRelease": "2023",
        "authors": ["Zephyrus Edavane"],
        "singleplayer": false,
        "minPlayers": "2",
        "maxPlayers": "8",
        "type": "cooperative"
      }
    ]
  }
]
